{
    "models/property_friends_v1.pkl": {
        "RMSE": 10210.638544597201,
        "MAPE": 0.9700475653886999,
        "MAE": 6689.489211064686,
        "timestamp": "2024-12-23T16:13:18.155875"
    },
    "models/property_friends_v2.pkl": {
        "RMSE": 10210.638544597201,
        "MAPE": 0.9700475653886999,
        "MAE": 6689.489211064686,
        "timestamp": "2024-12-23T16:13:30.136140"
    },
    "models/property_friends_v3.pkl": {
        "RMSE": 10210.638544597201,
        "MAPE": 0.9700475653886999,
        "MAE": 6689.489211064687,
        "timestamp": "2024-12-23T16:14:25.737928"
    },
    "models/property_friends_v4.joblib": {
        "RMSE": 10210.6385445972,
        "MAPE": 0.9700475653887,
        "MAE": 6689.489211064687,
        "timestamp": "2024-12-23T16:14:39.821610"
    },
    "models/property_friends_v5.joblib": {
        "RMSE": 10210.638544597201,
        "MAPE": 0.9700475653887,
        "MAE": 6689.489211064687,
        "timestamp": "2024-12-23T16:15:45.515937"
    },
    "models/property_friends_v6.joblib": {
        "RMSE": 10210.6385445972,
        "MAPE": 0.9700475653886999,
        "MAE": 6689.489211064687,
        "timestamp": "2024-12-23T17:03:40.975262"
    },
    "models/property_friends_v7.joblib": {
        "RMSE": 10210.6385445972,
        "MAPE": 0.9700475653887,
        "MAE": 6689.489211064687,
        "timestamp": "2024-12-23T17:04:08.117232"
    },
    "models/property_friends_v8.joblib": {
        "RMSE": 10210.6385445972,
        "MAPE": 0.9700475653887,
        "MAE": 6689.489211064687,
        "timestamp": "2024-12-23T17:48:10.364498"
    },
    "models/property_friends_v9.pkl": {
        "RMSE": 10810.512797557823,
        "MAPE": 0.6386358045361223,
        "MAE": 6716.468206493688,
        "timestamp": "2024-12-25T15:57:01.302431"
    },
    "models/property_friends_v10.pkl": {
        "RMSE": 10810.512797557823,
        "MAPE": 0.6386358045361223,
        "MAE": 6716.468206493689,
        "timestamp": "2024-12-25T15:57:17.683942"
    },
    "models/property_friends_v11.pkl": {
        "RMSE": 10810.512797557823,
        "MAPE": 0.6386358045361225,
        "MAE": 6716.468206493689,
        "timestamp": "2024-12-25T16:39:54.555989"
    },
    "models/property_friends_v12.pkl": {
        "RMSE": 10810.512797557823,
        "MAPE": 0.6386358045361223,
        "MAE": 6716.468206493689,
        "timestamp": "2024-12-25T16:40:08.632124"
    },
    "models/property_friends_v13.pkl": {
        "RMSE": 9994.05949771598,
        "MAPE": 9000755441099054.0,
        "MAE": 6636.049514733151,
        "timestamp": "2024-12-25T16:44:09.655165"
    },
    "models/property_friends_v14.pkl": {
        "RMSE": 9994.05949771598,
        "MAPE": 9000755441099054.0,
        "MAE": 6636.04951473315,
        "timestamp": "2024-12-25T16:46:25.543885"
    },
    "models/property_friends_v15.pkl": {
        "RMSE": 9994.05949771598,
        "MAPE": 9000755441099054.0,
        "MAE": 6636.04951473315,
        "timestamp": "2024-12-25T16:52:35.539281"
    },
    "models/property_friends_v16.pkl": {
        "RMSE": 9994.05949771598,
        "MAPE": 9000755441099054.0,
        "MAE": 6636.04951473315,
        "timestamp": "2024-12-25T16:53:37.148648"
    },
    "models/property_friends_v17.pkl": {
        "RMSE": 9994.05949771598,
        "MAPE": 9000755441099054.0,
        "MAE": 6636.049514733151,
        "timestamp": "2024-12-25T19:04:53.559352"
    }
}